webpic/__init__.py
webpic/main.py
webpic-0.1.3.dist-info/METADATA
webpic-0.1.3.dist-info/WHEEL
webpic-0.1.3.dist-info/entry_points.txt
webpic-0.1.3.dist-info/top_level.txt
webpic-0.1.3.dist-info/RECORD
